antchain_sdk_ak_e27b711821a94d8d95c0c869fc28e0d3/__init__.py
antchain_sdk_ak_e27b711821a94d8d95c0c869fc28e0d3/client.py
antchain_sdk_ak_e27b711821a94d8d95c0c869fc28e0d3/models.py
antchain_ak_e27b711821a94d8d95c0c869fc28e0d3-1.0.0.dist-info/LICENSE
antchain_ak_e27b711821a94d8d95c0c869fc28e0d3-1.0.0.dist-info/METADATA
antchain_ak_e27b711821a94d8d95c0c869fc28e0d3-1.0.0.dist-info/WHEEL
antchain_ak_e27b711821a94d8d95c0c869fc28e0d3-1.0.0.dist-info/top_level.txt
antchain_ak_e27b711821a94d8d95c0c869fc28e0d3-1.0.0.dist-info/RECORD
